{ "spaceFlix": [
    {
        "id": 1,
        "title": "The Joker | Tráiler Oficial",
        "capa": "https://encrypted-tbn0.gstatic.com/images?q=tbn:ANd9GcRHrEYNFWxHq9dGjsB_MES1tacGgSPX6WXnwg&s",
        "video": "https://www.youtube.com/watch?v=GD4RVzGgfbQ",
        "category": "Trailer",
        "description": "Red One es una próxima película navideña estadounidense de acción y aventuras."
    },
    {
        "id": 2,
        "title": "The Batman | Tráiler Oficial",
        "capa": "https://encrypted-tbn0.gstatic.com/images?q=tbn:ANd9GcTtuJ80apLEAudM9mBiqd8Ji1K0XzktMvt-lA&s",
        "video": "https://www.youtube.com/watch?v=5fExaDWYEGc",
        "category": "Trailer",
        "description": "Red One es una próxima película navideña estadounidense de acción y aventuras."
    },
    {
        "id": 3,
        "title": "MAtrix Resurrections | Tráiler Oficial",
        "capa": "https://encrypted-tbn0.gstatic.com/images?q=tbn:ANd9GcQVyVrLg7ACcotgkTyGE2TfFkt6JczbMg194Q&s",
        "video": "https://www.youtube.com/watch?v=kGLfnrqsqII",
        "category": "Trailer",
        "description": "Red One es una próxima película navideña estadounidense de acción y aventuras."
    },
    {
        "id": 4,
        "title": "The Batman | Tráiler Oficial",
        "capa": "https://encrypted-tbn0.gstatic.com/images?q=tbn:ANd9GcTYb0U_TSN_8qcROIZEbz2m8cWrZEyfy81b3w&s",
        "video": "https://www.youtube.com/watch?v=YebuQmmQkyw",
        "category": "Música",
        "description": "Red One es una próxima película navideña estadounidense de acción y aventuras."
    },
    {
        "id": 5,
        "title": "Un lugar en silencio: Día uno | Tráiler Oficial",
        "capa": "https://encrypted-tbn0.gstatic.com/images?q=tbn:ANd9GcSr1_vM_Z6dQ2PxeTUbc9lJE30g1XcJwX8ujw&s",
        "video": "https://www.youtube.com/watch?v=E-WIb4ATfT8",
        "category": "Música",
        "description": "Red One es una próxima película navideña estadounidense de acción y aventuras."
    },
    {
        "id": 5,
        "title": "Alien: Romulus | Tráiler Oficial",
        "capa": "https://encrypted-tbn0.gstatic.com/images?q=tbn:ANd9GcQlBdk_XnRfqYZzFocRsNx_MaUBD1mygKHs2Q&s",
        "video": "https://www.youtube.com/watch?v=kTpc5SoBVu0",
        "category": "Trailer",
        "description": "Red One es una próxima película navideña estadounidense de acción y aventuras."
    },
    {
        "id": 6,
        "title": "Happiness",
        "capa": "https://catholic-link.com/wp-content/uploads/2017/12/ratas.jpg",
        "video": "https://www.youtube.com/watch?v=e9dZQelULDk",
        "category": "Cortometrajes",
        "description": "Red One es una próxima película navideña estadounidense de acción y aventuras."
    },
    {
        "id": 7,
        "title": "Loop",
        "capa": "https://lacriaturacreativa.com/wp-content/uploads/2023/02/LOOP-00.png",
        "video": "https://www.youtube.com/watch?v=ijq_UkRKSFw&t=114s",
        "category": "Cortometrajes",
        "description": "Red One es una próxima película navideña estadounidense de acción y aventuras."
    }
]}
